pageweaver/__init__.py
pageweaver/document_generator.py
pageweaver/novel_crawler_service.py
pageweaver/text_processor.py
pageweaver/web_crawler.py
pageweaver-1.1.1.dist-info/LICENSE
pageweaver-1.1.1.dist-info/METADATA
pageweaver-1.1.1.dist-info/WHEEL
pageweaver-1.1.1.dist-info/entry_points.txt
pageweaver-1.1.1.dist-info/top_level.txt
pageweaver-1.1.1.dist-info/RECORD
